kamaaalpy/__init__.py
kamaaalpy/dicts.py
kamaaalpy/files.py
kamaaalpy/lists.py
kamaalpy-0.3.0.dist-info/licenses/LICENSE
kamaalpy-0.3.0.dist-info/METADATA
kamaalpy-0.3.0.dist-info/WHEEL
kamaalpy-0.3.0.dist-info/top_level.txt
kamaalpy-0.3.0.dist-info/RECORD
