Metadata-Version: 2.4
Name: kamaalpy
Version: 0.3.0
Summary: A package with everything Python
Author-email: Kamaal Farah <kamaal.f1@gmail.com>
License: MIT License
Project-URL: Homepage, https://github.com/Kamaalio/KamaalPy
Project-URL: Bug Tracker, https://github.com/Kamaalio/KamaalPy/issues
Classifier: Programming Language :: Python :: 3
Classifier: License :: OSI Approved :: MIT License
Classifier: Operating System :: OS Independent
Requires-Python: >=3.11
License-File: LICENSE
Dynamic: license-file
